<?xml version="1.0" encoding="utf-8"?>
<page code="classgroupmodify" title="小组信息修改" path="branch"  jellyinject="app.drz.org.sview.classgroupmodify"><data id="group"  import="drzgroup" iterator="object" createnew="true" ><parameter name="where"  value="@{_jelly.prop_data_group_parmwhere_value()}" /></data><layout generator="auto"  ></layout><widget id="subgroupname" title="小组名称" container="container1" bind="@{_jelly.prop_wgt_subgroupname_bind()}" required="false" ><text /></widget><widget id="subgroupdiscription" title="小组简述" container="container1" bind="@{_jelly.prop_wgt_subgroupdiscription_bind()}" required="false" ><textarea /></widget><widget id="submitbutton" title="" container="container2" bind="提交" ><button /></widget><widget id="back" title="" container="container2" bind="返回" ><button /></widget><event when="create"><![CDATA[_jelly.event_create()]]></event><event when="pager"><![CDATA[_jelly.event_pager()]]></event><event when="submit"><![CDATA[_jelly.event_submit()]]></event><action  target="back" type="click" do="submit" ></action><action  type="click" target="submitbutton" do="submit" ></action><transfer  on="@{_jelly.prop_trans_toclassgrouplabel_on()}" to="classgrouplabel" /><transfer  on="@{_jelly.prop_trans_backtoclassgrouplabel_on()}" to="classgrouplabel" /></page>